{"hash":"431d1187f237bae63d75b35204704e585def61a3","data":{"wordPressPost":{"title":"Самообучение електроника &#8211; предварителна сбирка","content":"<p><strong>Четвъртък, 19 Май, 19:00 в &#8222;сървърното&#8220; на Лаба</strong>.  Ще организираме импровизирана среща, на която ще обсъдим в детайли как ще се проведе самообучителния курс по електроника, за който инициатори сме Мартин Райков и Радослав Борисов.  Целта на курса ще бъде въвеждане в електрониката и провеждане на ежеседмични практически сбирки, на които ще се реализират различни хардуерни проекти.  Курсът ще бъде безплатен!</p>\n","featuredMedia":null,"categories":[{"id":"10","title":"Новини","path":"/category/news/"}],"tags":[]}},"context":{}}