{"hash":"431d1187f237bae63d75b35204704e585def61a3","data":{"wordPressCategory":{"title":"Новини","belongsTo":{"pageInfo":{"totalPages":16,"currentPage":12},"edges":[{"node":{"id":"451","title":"Въвеждащ Java Workshop","path":"/2009/10/29/d0-b2-d1-8a-d0-b2-d0-b5-d0-b6-d0-b4-d0-b0-d1-89-java-workshop/","excerpt":"<p>Съвместно с колегите от FOSSCourse, които тази есен провеждащ въвеждащ курс в програмирането на Java в Техническия Университет, организираме workshop на Java, в който&#46;&#46;&#46;</p>\n"}},{"node":{"id":"447","title":"BSDCon @ OpenFest 2009","path":"/2009/10/27/bsdcon-openfest-2009/","excerpt":"<p>По време на феста на 7-ми ноември ще се проведе успоредно и конференция на българските потребители и фенове на BSD &#8211; BSDCon. Следва предварителната&#46;&#46;&#46;</p>\n"}},{"node":{"id":"439","title":"sofia.rb @ The Pirate Bay","path":"/2009/10/16/sofia-rb-the-pirate-bay/","excerpt":"<p>След поредния неуспех да се задържим в заведение, където програмистите се възприемат като лоша поличба, стигнахме до заключението, че ни трябва нещо по-нашенско. Нещо&#46;&#46;&#46;</p>\n"}},{"node":{"id":"432","title":"Къде се случва GameDev Workshop 1.1","path":"/2009/10/16/d0-ba-d1-8a-d0-b4-d0-b5-d1-81-d0-b5-d1-81-d0-bb-d1-83-d1-87-d0-b2-d0-b0-gamedev-workshop-1-1/","excerpt":"<p>Вече стана официално ясно, че работилницата на клуба по разработка на игри ще се провежда в Лаба (сиреч зала 100). Както вече писах &#8211;&#46;&#46;&#46;</p>\n"}},{"node":{"id":"426","title":"Linux Install Fest отново","path":"/2009/10/16/linux-install-fest-d0-be-d1-82-d0-bd-d0-be-d0-b2-d0-be/","excerpt":"<p>За пореден път наши приятели организират ден за инсталация на Линукс дистрибуции, а по между другото и за борба за актуални проблеми по Линукс-машината.&#46;&#46;&#46;</p>\n"}},{"node":{"id":"416","title":"Книга &#8222;Въведение в програмирането с Java&#8220;","path":"/2009/10/14/d0-ba-d0-bd-d0-b8-d0-b3-d0-b0-d0-b2-d1-8a-d0-b2-d0-b5-d0-b4-d0-b5-d0-bd-d0-b8-d0-b5-d0-b2-d0-bf-d1-80-d0-be-d0-b3-d1-80-d0-b0-d0-bc-d0-b8-d1-80-d0-b0-d0-bd-d0-b5-d1-82-d0-be-d1-81-java/","excerpt":"<p>Официално беше пусната книгата за Java, чието написване бе инициирано и ръководено от Светлин Наков, а изпълнението бе от двадесет софтуериста, пожелали да допринесат&#46;&#46;&#46;</p>\n"}},{"node":{"id":"410","title":"Промяна на мястото на sofia.rb","path":"/2009/10/13/d0-bf-d1-80-d0-be-d0-bc-d1-8f-d0-bd-d0-b0-d0-bd-d0-b0-d0-bc-d1-8f-d1-81-d1-82-d0-be-d1-82-d0-be-d0-bd-d0-b0-sofia-rb/","excerpt":"<p>Първата за сезона Ruby среща мина кротко, но и малко по номадски. След като на мнозинството заведението, където бяхме, не се хареса, се преместихме&#46;&#46;&#46;</p>\n"}},{"node":{"id":"411","title":"Workshop за разработка на игри","path":"/2009/10/09/workshop-d0-b7-d0-b0-d1-80-d0-b0-d0-b7-d1-80-d0-b0-d0-b1-d0-be-d1-82-d0-ba-d0-b0-d0-bd-d0-b0-d0-b8-d0-b3-d1-80-d0-b8/","excerpt":"<p>Game development клубът на ФМИ стартира workshop за въведение в разработката на игри на С# и OpenGL. Записването става с изпращане на писмо до&#46;&#46;&#46;</p>\n"}},{"node":{"id":"408","title":"Подновяване на sofia.rb","path":"/2009/10/05/d0-bf-d0-be-d0-b4-d0-bd-d0-be-d0-b2-d1-8f-d0-b2-d0-b0-d0-bd-d0-b5-d0-bd-d0-b0-sofia-rb/","excerpt":"<p>След лятната ваканция и известна доза ослушване ежеседмичната вечер на Ruby (че и по релси) програмирането. Ключовата дума е sofia.rb, а мястото е Клуба&#46;&#46;&#46;</p>\n"}},{"node":{"id":"399","title":"Хакатони на всеки две седмици!","path":"/2009/10/03/d1-85-d0-b0-d0-ba-d0-b0-d1-82-d0-be-d0-bd-d0-b8-d0-bd-d0-b0-d0-b2-d1-81-d0-b5-d0-ba-d0-b8-d0-b4-d0-b2-d0-b5-d1-81-d0-b5-d0-b4-d0-bc-d0-b8-d1-86-d0-b8/","excerpt":"<p>Последният хакатон се получи повече от интересен и в края на крайщата преценихме, че е най-добре да се установи официален отговор на постоянно задавания&#46;&#46;&#46;</p>\n"}}]}}},"context":{}}